hardshell/__init__.py
hardshell/__main__.py
hardshell/config/hardshell.toml
hardshell/scanner/__init__.py
hardshell/scanner/linux.py
hardshell/scanner/scanner.py
hardshell/scanner/windows.py
hardshell/utils/config.py
hardshell/utils/core.py
hardshell/utils/logger.py
hardshell/utils/report.py
hardshell/utils/startup.py
hardshell/utils/utilities.py
hardshell-0.1.4.dist-info/LICENSE
hardshell-0.1.4.dist-info/METADATA
hardshell-0.1.4.dist-info/WHEEL
hardshell-0.1.4.dist-info/entry_points.txt
hardshell-0.1.4.dist-info/RECORD
